nodesemver/__init__.py
node_semver-0.9.0.dist-info/LICENSE
node_semver-0.9.0.dist-info/METADATA
node_semver-0.9.0.dist-info/WHEEL
node_semver-0.9.0.dist-info/entry_points.txt
node_semver-0.9.0.dist-info/top_level.txt
node_semver-0.9.0.dist-info/RECORD
