Metadata-Version: 2.1
Name: node-semver
Version: 0.9.0
Summary: port of node-semver
Home-page: https://github.com/podhmo/python-node-semver
Author: podhmo
Author-email: ababjam61+github@gmail.com
License: mit
Keywords: version semver node-semver
Platform: UNKNOWN
Classifier: Programming Language :: Python
Classifier: Programming Language :: Python :: 3
Classifier: Programming Language :: Python :: Implementation :: CPython
Provides-Extra: docs
Provides-Extra: testing
License-File: LICENSE
